setup.py
testless_textanalyzer.egg-info/PKG-INFO
testless_textanalyzer.egg-info/SOURCES.txt
testless_textanalyzer.egg-info/dependency_links.txt
testless_textanalyzer.egg-info/requires.txt
testless_textanalyzer.egg-info/top_level.txt
textanalyzer/__init__.py
textanalyzer/testless_textanalyzer/__init__.py
textanalyzer/testless_textanalyzer/crf.py
textanalyzer/testless_textanalyzer/crf_utils.py
textanalyzer/testless_textanalyzer/exceptions.py
textanalyzer/testless_textanalyzer/feature.py
textanalyzer/testless_textanalyzer/read_data.py
textanalyzer/testless_textanalyzer/text_analyzer.py