Metadata-Version: 2.1
Name: testless-textanalyzer
Version: 0.1.9
Summary: A text analyzer for test step sentences
Author: Youssef Ahmed
License: MIT
Classifier: License :: OSI Approved :: MIT License
Classifier: Programming Language :: Python :: 3.10
Classifier: Operating System :: OS Independent
